box_embeddings/__init__.py
box_embeddings/common/__init__.py
box_embeddings/common/constant.py
box_embeddings/common/registrable.py
box_embeddings/common/tf_utils.py
box_embeddings/common/utils.py
box_embeddings/initializations/__init__.py
box_embeddings/initializations/initializer.py
box_embeddings/initializations/tf_initializer.py
box_embeddings/initializations/tf_uniform_boxes.py
box_embeddings/initializations/uniform_boxes.py
box_embeddings/modules/__init__.py
box_embeddings/modules/box_module.py
box_embeddings/modules/embedding.py
box_embeddings/modules/tf_embedding.py
box_embeddings/modules/intersection/__init__.py
box_embeddings/modules/intersection/_intersection.py
box_embeddings/modules/intersection/_tf_intersection.py
box_embeddings/modules/intersection/gumbel_intersection.py
box_embeddings/modules/intersection/hard_intersection.py
box_embeddings/modules/intersection/intersection.py
box_embeddings/modules/intersection/tf_gumbel_intersection.py
box_embeddings/modules/intersection/tf_hard_intersection.py
box_embeddings/modules/intersection/tf_intersection.py
box_embeddings/modules/pooling/__init__.py
box_embeddings/modules/pooling/bag_of_boxes.py
box_embeddings/modules/pooling/intersection.py
box_embeddings/modules/pooling/pooling.py
box_embeddings/modules/pooling/tf_bag_of_boxes.py
box_embeddings/modules/pooling/tf_intersection.py
box_embeddings/modules/pooling/tf_pooling.py
box_embeddings/modules/regularization/__init__.py
box_embeddings/modules/regularization/l2_side_regularizer.py
box_embeddings/modules/regularization/regularizer.py
box_embeddings/modules/regularization/tf_l2_side_regularizer.py
box_embeddings/modules/regularization/tf_regularizer.py
box_embeddings/modules/volume/__init__.py
box_embeddings/modules/volume/_tf_volume.py
box_embeddings/modules/volume/_volume.py
box_embeddings/modules/volume/bessel_volume.py
box_embeddings/modules/volume/hard_volume.py
box_embeddings/modules/volume/soft_volume.py
box_embeddings-0.1.0.dist-info/METADATA
box_embeddings-0.1.0.dist-info/WHEEL
box_embeddings-0.1.0.dist-info/top_level.txt
box_embeddings-0.1.0.dist-info/RECORD
