Metadata-Version: 2.1
Name: box-embeddings
Version: 0.1.0
Summary: Pytorch and Tensorflow implemention of box embedding models
Home-page: http://www.iesl.cs.umass.edu/box-embeddings/
Author: Dhruvesh Patel, Shib Sankar Dasgupta, Michael Boratko, Purujit Goyal, Tejas Chheda, Trang Tran, Xiang (Lorraine) Li
Author-email: 1793dnp@gmail.com
License: UNKNOWN
Project-URL: Documentation, http://www.iesl.cs.umass.edu/box-embeddings
Project-URL: Source Code, https://github.com/iesl/box-embeddings
Keywords: pytorch,tensorflow,AI,ML,Machine Learning,Deep Learning
Platform: UNKNOWN
Classifier: Programming Language :: Python :: 3
Classifier: License :: OSI Approved :: MIT License
Classifier: Operating System :: OS Independent
Classifier: Development Status :: 3 - Alpha
Classifier: Intended Audience :: Developers
Classifier: Intended Audience :: Education
Classifier: Intended Audience :: Science/Research
Classifier: Topic :: Scientific/Engineering :: Artificial Intelligence
Requires-Python: >=3.5
Requires-Dist: torch (>=1.6.0)
Requires-Dist: numpy
